Workbook

Sheet Instrucciones
B2: EVALUACION HEURISTICA DE USABILIDAD - NIELSEN
B3: Ingenieria de Software - Calidad y Pruebas - Plantilla de Evaluacion
B5: INSTRUCCIONES DE USO
B6: 1. Complete los datos del equipo evaluador en esta hoja.
B7: 2. Navegue por el MVP asignado durante al menos 20 minutos antes de evaluar.
B8: 3. Use la hoja 'Evaluacion' para registrar todos los problemas encontrados.
B9: 4. Para cada problema, asigne una severidad segun la escala de Nielsen (0 a 4).
B10: 5. Documente con capturas de pantalla o notas descriptivas en la columna Evidencia.
B11: 6. La hoja 'Resumen' se actualiza automaticamente al completar la evaluacion.
B12: 7. La hoja 'Referencia' contiene los principios y ejemplos para consulta.
B15: ESCALA DE SEVERIDAD (Nielsen, 1994)
B16: 0 | C16: No es un problema de usabilidad
B17: 1 | C17: Problema cosmético | corregir solo si hay tiempo
B18: 2 | C18: Problema menor | baja prioridad de correccion
B19: 3 | C19: Problema mayor | alta prioridad, dificulta el uso
B20: 4 | C20: CATASTROFICO | imperativo corregir antes del lanzamiento

Sheet Evaluacion
A1: REGISTRO DE PROBLEMAS DE USABILIDAD — EVALUACION HEURISTICA
A2: Complete una fila por cada problema encontrado. Puede agregar mas filas segun sea necesario.
A3: # | B3: Heuristica | C3: Descripcion del problema | D3: Ubicacion en el Prototipo | E3: Severidad (0-4) | F3: Evidencia (captura/URL) | G3: Recomendacion de mejora | H3: Evaluador
A4: 1 | B4: H1 - Visibilidad del estado | C4: el login estaba segmentado en torre como si fuera un condominio pero al ser un solo edificio era totalmente opuesto a la realidad | D4: inicio de sesion (login) | E4: 3 | F4: evidencia 1.png | G4: utilizar numeros compuestos por el numero del piso y el numero del orden del piso para el numero de los respectivos departamentos . | H4: ignacio reyes
A5: 2 | B5: H2 - Sistema y mundo real | C5: la funcion de pago era un ingreso directo y deberia redirigir a los servicios de web pay para mayor seguridad | D5: portal de pago | E5: 3 | F5: evidencia 2.png | G5: hacer que la funcion de pagar sea redirigida a webpay para el mismo la procese | H5: ignacio reyes
A6: 3 | B6: H2 - Sistema y mundo real | C6: al momento de ingresar los datos de la tarjeta funcionaba con cualquien dato que se ingresara y procesaba el pago | D6: portal de pago | E6: 4 | F6: evidencia 3.png | G6: agregar validaciones para los numeros de tarjeta, que la fecha de vencimiento no sea inferior a la fecha actual y que el cvv sea un numero valido | H6: joaquin
A7: 4 | B7: H3 - Control y libertad | C7: segun el enunciado el administrador deberia poder agregar cobros especiales y estos deberian ser reflejados en los cobros del residente | D7: perfil administrador | E7: 2 | F7: evidencia 4.png | G7: agregar la opcion del agregar un cobro especial junto a su respectiva descripcion en el perfil del administrador | H7: francisco
A8: 5 | B8: H1 - Visibilidad del estado | C8: las alarmas de alerta al inicio saturan mucho el perfil de administrador | D8: perfil administrador | E8: 2 | F8: evidencia 5.png | G8: crear una pestaña aparte dentro del perfil de administrador donde se pueda ver las alertas | H8: joaquin
A9: 6 | B9: H8 - Diseno minimalista | C9: es dificil ver la forma de cancelar la transaccion | D9: portal de pago (web pay) | E9: 3 | F9: evidencia 6.png | G9: cambiar el cancelar transaccion para que sea ams intuitiva | H9: joaquin
A10: 7 | B10: H5 - Prevencion de errores | C10: te permite ingresar mas datos de los que poseen las tarjetas antes de rechazar la transaccion | D10: portal de pago (web pay) | E10: 3 | F10: evidencia 7.png | G10: limitar los digitos que permita ingresar a 16 que es la cantidad de digitos que posee el numero de las tarjetas | H10: francisco
A11: 8 | B11: H6 - Reconocimiento > recuerdo | C11: la opcion de pagos en cuotas es poco intuitiva | D11: portal de pago (web pay) | E11: 2 | F11: evidencia 8.png | G11: colocar la opcion de pagos en cuotas de una forma mas clara | H11: ignacio reyes
A12: 9 | B12: H7 - Flexibilidad y eficiencia | C12: es tardado para los propietarios tener que pagar las cuentas de sus departamentos en caso que el propietario posea mas de un departamento | D12: inicio de sesion (login) | E12: 3 | F12: evidencia 9.png | G12: generar un nuevo perfil que permita entrar como propietario | H12: francisco
A13: 10 | B13: H1 - Visibilidad del estado | C13: deberia mostrar la deuda sin necesidad de ingresesar al respectivo departamento | D13: perfil propietario | E13: 2 | G13: hacer que los departamentos posean una previsualizacion de la deuda
A14: 11 | B14: H1 - Visibilidad del estado | C14: los departamentos que no poseen deuda muestra su deuda lo que satura un poco | D14: perfil propietario | E14: 1 | G14: hacer que los departamentos que no posean deudas muestre el mensaje al dia en un color diferente

Sheet Resumen
B1: RESUMEN EJECUTIVO EVALUACION HEURISTICA
B2: Los valores se calculan automaticamente desde la hoja Evaluacion
B4: METRICAS GLOBALES
B5: Total de problemas registrados | C5: =COUNTA(Evaluacion!C4:C14) -> 11
B6: Promedio de severidad | C6: =IFERROR(AVERAGE(Evaluacion!E4:E14),0) -> 2.5454545
B7: Problemas catastroficos (sev. 4) | C7: =COUNTIF(Evaluacion!E4:E14,4) -> 1
B8: Problemas mayores (sev. 3) | C8: =COUNTIF(Evaluacion!E4:E14,3) -> 5
B9: Problemas menores (sev. 1-2) | C9: =COUNTIFS(Evaluacion!E4:E14,">=1",Evaluacion!E4:E14,"<=2") -> 5
B11: DISTRIBUCION POR HEURISTICA
B12: Heuristica | C12: # Problemas | D12: Sev. Max. | E12: Sev. Prom. | F12: Estado | G12: Prioridad
B13: H1 - Visibilidad del estado | C13: 1 | D13: 1 | E13: 1 | F13: =IF(C13=0,"Sin problemas",IF(D13>=4,"CRITICO",IF(D13>=3,"MAYOR","MENOR"))) -> MENOR | G13: =IF(C13=0,"Sin problemas",IF(D13=4,"1 - Inmediata",IF(D13=3,"2 - Alta",IF(D13=2,"3 - Media","4 - Baja")))) -> 4 - Baja
B14: H2 - Sistema y mundo real | C14: =COUNTIF(Evaluacion!B4:B14,"*H2*") -> 2 | D14: =IFERROR(_xludf.MAXIFS(Evaluacion!E4:E14,Evaluacion!B4:B14,"*H2*"),0) -> 0 | E14: =IFERROR(AVERAGEIF(Evaluacion!B4:B14,"*H2*",Evaluacion!E4:E14),0) -> 3.5 | F14: =IF(C14=0,"Sin problemas",IF(D14>=4,"CRITICO",IF(D14>=3,"MAYOR","MENOR"))) -> MENOR | G14: =IF(C14=0,"Sin problemas",IF(D14=4,"1 - Inmediata",IF(D14=3,"2 - Alta",IF(D14=2,"3 - Media","4 - Baja")))) -> 4 - Baja
B15: H3 - Control y libertad | C15: 1 | D15: 2 | E15: 2 | F15: =IF(C15=0,"Sin problemas",IF(D15>=4,"CRITICO",IF(D15>=3,"MAYOR","MENOR"))) -> MENOR | G15: =IF(C15=0,"Sin problemas",IF(D15=4,"1 - Inmediata",IF(D15=3,"2 - Alta",IF(D15=2,"3 - Media","4 - Baja")))) -> 3 - Media
B16: H4 - Consistencia y estandares | C16: =COUNTIF(Evaluacion!B4:B14,"*H4*") -> 0 | D16: =IFERROR(_xludf.MAXIFS(Evaluacion!E4:E14,Evaluacion!B4:B14,"*H4*"),0) -> 0 | E16: =IFERROR(AVERAGEIF(Evaluacion!B4:B14,"*H4*",Evaluacion!E4:E14),0) -> 0 | F16: =IF(C16=0,"Sin problemas",IF(D16>=4,"CRITICO",IF(D16>=3,"MAYOR","MENOR"))) -> Sin problemas | G16: =IF(C16=0,"Sin problemas",IF(D16=4,"1 - Inmediata",IF(D16=3,"2 - Alta",IF(D16=2,"3 - Media","4 - Baja")))) -> Sin problemas
B17: H5 - Prevencion de errores | C17: 1 | D17: 2 | E17: 2 | F17: =IF(C17=0,"Sin problemas",IF(D17>=4,"CRITICO",IF(D17>=3,"MAYOR","MENOR"))) -> MENOR | G17: =IF(C17=0,"Sin problemas",IF(D17=4,"1 - Inmediata",IF(D17=3,"2 - Alta",IF(D17=2,"3 - Media","4 - Baja")))) -> 3 - Media
B18: H6 - Reconocimiento > recuerdo | C18: =COUNTIF(Evaluacion!B4:B14,"*H6*") -> 1 | D18: =IFERROR(_xludf.MAXIFS(Evaluacion!E4:E14,Evaluacion!B4:B14,"*H6*"),0) -> 0 | E18: =IFERROR(AVERAGEIF(Evaluacion!B4:B14,"*H6*",Evaluacion!E4:E14),0) -> 2 | F18: =IF(C18=0,"Sin problemas",IF(D18>=4,"CRITICO",IF(D18>=3,"MAYOR","MENOR"))) -> MENOR | G18: =IF(C18=0,"Sin problemas",IF(D18=4,"1 - Inmediata",IF(D18=3,"2 - Alta",IF(D18=2,"3 - Media","4 - Baja")))) -> 4 - Baja
B19: H7 - Flexibilidad y eficiencia | C19: =COUNTIF(Evaluacion!B4:B14,"*H7*") -> 1 | D19: =IFERROR(_xludf.MAXIFS(Evaluacion!E4:E14,Evaluacion!B4:B14,"*H7*"),0) -> 0 | E19: =IFERROR(AVERAGEIF(Evaluacion!B4:B14,"*H7*",Evaluacion!E4:E14),0) -> 3 | F19: =IF(C19=0,"Sin problemas",IF(D19>=4,"CRITICO",IF(D19>=3,"MAYOR","MENOR"))) -> MENOR | G19: =IF(C19=0,"Sin problemas",IF(D19=4,"1 - Inmediata",IF(D19=3,"2 - Alta",IF(D19=2,"3 - Media","4 - Baja")))) -> 4 - Baja
B20: H8 - Diseno minimalista | C20: =COUNTIF(Evaluacion!B4:B14,"*H8*") -> 1 | D20: =IFERROR(_xludf.MAXIFS(Evaluacion!E4:E14,Evaluacion!B4:B14,"*H8*"),0) -> 0 | E20: =IFERROR(AVERAGEIF(Evaluacion!B4:B14,"*H8*",Evaluacion!E4:E14),0) -> 3 | F20: =IF(C20=0,"Sin problemas",IF(D20>=4,"CRITICO",IF(D20>=3,"MAYOR","MENOR"))) -> MENOR | G20: =IF(C20=0,"Sin problemas",IF(D20=4,"1 - Inmediata",IF(D20=3,"2 - Alta",IF(D20=2,"3 - Media","4 - Baja")))) -> 4 - Baja
B21: H9 - Recuperacion de errores | C21: =COUNTIF(Evaluacion!B4:B14,"*H9*") -> 0 | D21: =IFERROR(_xludf.MAXIFS(Evaluacion!E4:E14,Evaluacion!B4:B14,"*H9*"),0) -> 0 | E21: =IFERROR(AVERAGEIF(Evaluacion!B4:B14,"*H9*",Evaluacion!E4:E14),0) -> 0 | F21: =IF(C21=0,"Sin problemas",IF(D21>=4,"CRITICO",IF(D21>=3,"MAYOR","MENOR"))) -> Sin problemas | G21: =IF(C21=0,"Sin problemas",IF(D21=4,"1 - Inmediata",IF(D21=3,"2 - Alta",IF(D21=2,"3 - Media","4 - Baja")))) -> Sin problemas
B22: H10 - Ayuda y documentacion | C22: 1 | D22: 1 | E22: 1 | F22: =IF(C22=0,"Sin problemas",IF(D22>=4,"CRITICO",IF(D22>=3,"MAYOR","MENOR"))) -> MENOR | G22: =IF(C22=0,"Sin problemas",IF(D22=4,"1 - Inmediata",IF(D22=3,"2 - Alta",IF(D22=2,"3 - Media","4 - Baja")))) -> 4 - Baja

Sheet Referencia
B1: REFERENCIA RAPIDA — 10 HEURISTICAS DE NIELSEN
B2: Consulta este panel mientras evaluas el MVP. Los ejemplos son orientativos para sistemas web/movil.
B3: # | C3: Heuristica | D3: Descripcion del principio | E3: Ejemplo en MVP (buena practica) | F3: Señal de problema a registrar
B4: H1 | C4: Visibilidad del estado | D4: El sistema mantiene informado al usuario sobre lo que ocurre mediante feedback oportuno. | E4: Barra de progreso al subir archivos. Spinner de carga. Toast de confirmacion al guardar datos. | F4: Boton que no responde visualmente. Sin indicador de carga. Usuario no sabe si la accion funciono.
B5: H2 | C5: Sistema y mundo real | D5: El sistema usa el lenguaje del usuario: palabras y conceptos familiares, no tecnicos. | E5: Icono de carrito para compras. 'Papelera' para eliminar. Fechas en formato dd/mm/aaaa. | F5: Mensajes tecnicos: 'Error 403 Forbidden'. Terminos internos del sistema expuestos al usuario.
B6: H3 | C6: Control y libertad | D6: El usuario puede salir de acciones no deseadas con salidas de emergencia claras. | E6: Opcion Deshacer al eliminar elemento. Boton Cancelar en formularios. Navegacion por pasos reversible. | F6: Sin forma de cancelar un proceso. Formulario sin boton Atras. Sin opcion de deshacer eliminacion.
B7: H4 | C7: Consistencia y estandares | D7: Las mismas acciones y elementos se comportan igual en todo el sistema. | E7: Boton primario mismo color en todo el sistema. Color rojo siempre indica error. Campos en mismo orden. | F7: Guardar, Registrar y Confirmar para la misma accion. Botones de distinto color por modulo.
B8: H5 | C8: Prevencion de errores | D8: El diseño evita que los errores ocurran antes de que el usuario los cometa. | E8: Campo deshabilitado si falta informacion. Confirmacion antes de eliminar. Validacion en tiempo real. | F8: Fecha 30/02 se acepta sin validar. Boton Enviar activo con campos requeridos vacios.
B9: H6 | C9: Reconocimiento > recuerdo | D9: Minimizar la carga de memoria: las opciones disponibles deben ser visibles, no memorizadas. | E9: Autocompletado en busquedas. Historial de elementos recientes. Breadcrumbs de navegacion. | F9: Usuario debe recordar sintaxis exacta. Formulario borra datos al navegar hacia atras.
B10: H7 | C10: Flexibilidad y eficiencia | D10: Atajos para expertos sin afectar la experiencia de usuarios nuevos. | E10: Atajos de teclado Ctrl+N. Filtros guardados. Exportacion masiva de datos con un clic. | F10: Solo se puede registrar de uno en uno. No hay forma de repetir la ultima accion ejecutada.
B11: H8 | C11: Diseño minimalista | D11: Solo la informacion necesaria: los elementos irrelevantes compiten por la atencion del usuario. | E11: Dashboard con 3 a 5 metricas clave. Formulario en pasos, no todo en una pantalla. | F11: 20 botones visibles simultaneamente. Panel con informacion que nunca se usa en el flujo principal.
B12: H9 | C12: Recuperacion de errores | D12: Los mensajes de error son claros, indican el problema exacto y sugieren una solucion concreta. | E12: 'El correo no tiene formato valido (ej: usuario@dominio.com)'. Enlace directo a solucion del error. | F12: 'Error 500'. 'Operacion fallida'. Mensaje generico sin indicar que hacer para resolverlo.
B13: H10 | C13: Ayuda y documentacion | D13: La ayuda es facil de encontrar, orientada a tareas concretas y accesible desde el flujo. | E13: Tooltip contextual en campos complejos. Guia de inicio rapido. FAQ con buscador integrado. | F13: Manual PDF de 80 paginas sin buscador. Ayuda solo accesible desde el menu principal oculto.
